override.py
overriden.py
overriden-0.1.3.dist-info/METADATA
overriden-0.1.3.dist-info/WHEEL
overriden-0.1.3.dist-info/top_level.txt
overriden-0.1.3.dist-info/RECORD
