Metadata-Version: 2.1
Name: overriden
Version: 0.1.3
Summary: overriden
Author: Vitalii Abetkin
Author-email: abvit89s@gmail.ru
License: MIT
